odoo/addons/mrp_workcenter_cost/README.rst
odoo/addons/mrp_workcenter_cost/__init__.py
odoo/addons/mrp_workcenter_cost/__manifest__.py
odoo/addons/mrp_workcenter_cost/i18n/it.po
odoo/addons/mrp_workcenter_cost/i18n/mrp_workcenter_cost.pot
odoo/addons/mrp_workcenter_cost/models/__init__.py
odoo/addons/mrp_workcenter_cost/models/mrp_production.py
odoo/addons/mrp_workcenter_cost/models/product_template.py
odoo/addons/mrp_workcenter_cost/readme/CONTRIBUTORS.rst
odoo/addons/mrp_workcenter_cost/readme/DESCRIPTION.rst
odoo/addons/mrp_workcenter_cost/readme/USAGE.rst
odoo/addons/mrp_workcenter_cost/static/description/icon.png
odoo/addons/mrp_workcenter_cost/static/description/index.html
odoo/addons/mrp_workcenter_cost/tests/__init__.py
odoo/addons/mrp_workcenter_cost/tests/test_mrp_workcenter_cost.py
odoo/addons/mrp_workcenter_cost/views/product_template.xml
odoo_addon_mrp_workcenter_cost-16.0.1.0.0.5.dist-info/METADATA
odoo_addon_mrp_workcenter_cost-16.0.1.0.0.5.dist-info/WHEEL
odoo_addon_mrp_workcenter_cost-16.0.1.0.0.5.dist-info/top_level.txt
odoo_addon_mrp_workcenter_cost-16.0.1.0.0.5.dist-info/RECORD
